catlist/catlist.py
simple_categories-0.1.2.dist-info/LICENSE.txt
simple_categories-0.1.2.dist-info/METADATA
simple_categories-0.1.2.dist-info/WHEEL
simple_categories-0.1.2.dist-info/top_level.txt
simple_categories-0.1.2.dist-info/RECORD
