Metadata-Version: 2.1
Name: simple-categories
Version: 0.1.2
Summary: Reads a categorized file and returns a dictionary
Home-page: https://gitlab.com/Nerdeiro/category-lists
Author: Bento Loewenstein Silveira
Author-email: anarch157a@ninjazumbi.com
License: GPL2
Platform: UNKNOWN
Classifier: License :: OSI Approved :: GNU General Public License v2 or later (GPLv2+)
Classifier: Programming Language :: Python :: 3
Classifier: Programming Language :: Python :: 3.8
